dev_ip-0.1.0.dist-info/METADATA
dev_ip-0.1.0.dist-info/RECORD
dev_ip-0.1.0.dist-info/WHEEL
dev_ip-0.1.0.dist-info/entry_points.txt
dev_ip-0.1.0.dist-info/top_level.txt
devip/__init__.py
devip/__main__.py
devip/lib.py
devip/main.py
